{
  "$schema": "corpusDocument.schema.json",
  "id": "be9c4235f99348c2947b7b8142daef43.doc",
  "metadata": {
    "title": "Tips & Trends : Des carnavals \u00e9cologiques | Metro",
    "sourceUrl": "https://fr.metrotime.be/2019/03/01/weekend/tips-trends-des-carnavals-ecologiques/",
    "documentSource": "fr.metrotime.be",
    "language": "en",
    "script": "lat",
    "datePublished": "2019-03-01",
    "monthPublished": "2019-03",
    "labels": [],
    "contentSource": "EventRegistry",
    "dateDownloaded": "2019-03",
    "dateIngested": ""
  }
}