{
  "$schema": "corpusDocument.schema.json",
  "id": "831ef3840b3a4e1685b2075d9b69293e.doc",
  "metadata": {
    "title": "Street vendors' self-help strategies highlight cities' neglect of how the other half survive - EconoTimes",
    "sourceUrl": "https://www.econotimes.com/Street-vendors-self-help-strategies-highlight-cities-neglect-of-how-the-other-half-survive-1504901",
    "documentSource": "econotimes.com",
    "language": "en",
    "script": "lat",
    "datePublished": "2019-03-01",
    "monthPublished": "2019-03",
    "labels": [],
    "contentSource": "EventRegistry",
    "dateDownloaded": "2019-03",
    "dateIngested": ""
  }
}