{
  "$schema": "corpus.schema.json",
  "documentId": "19706636624d450a94be3261d2a18eec.doc",
  "id": "19706636624d450a94be3261d2a18eec.terminals",
  "type": "terminal",
  "content": {
    "dataLayerRef": "19706636624d450a94be3261d2a18eec.data",
    "terminals": [
      {
        "start": 0,
        "end": 8,
        "string": "Algiers"
      },
      {
        "start": 8,
        "end": 9,
        "string": " "
      },
      {
        "start": 9,
        "end": 11,
        "string": ","
      },
      {
        "start": 11,
        "end": 12,
        "string": " "
      },
      {
        "start": 12,
        "end": 16,
        "string": "Mar"
      },
      {
        "start": 16,
        "end": 17,
        "string": " "
      },
      {
        "start": 17,
        "end": 19,
        "string": "1"
      },
      {
        "start": 19,
        "end": 20,
        "string": " "
      },
      {
        "start": 20,
        "end": 22,
        "string": "("
      },
      {
        "start": 22,
        "end": 23,
        "string": " "
      },
      {
        "start": 23,
        "end": 27,
        "string": "AFP"
      },
      {
        "start": 27,
        "end": 28,
        "string": " "
      },
      {
        "start": 28,
        "end": 30,
        "string": ")"
      },
      {
        "start": 30,
        "end": 31,
        "string": " "
      },
      {
        "start": 31,
        "end": 39,
        "string": "Several"
      },
      {
        "start": 39,
        "end": 40,
        "string": " "
      },
      {
        "start": 40,
        "end": 47,
        "string": "people"
      },
      {
        "start": 47,
        "end": 48,
        "string": " "
      },
      {
        "start": 48,
        "end": 53,
        "string": "were"
      },
      {
        "start": 53,
        "end": 54,
        "string": " "
      },
      {
        "start": 54,
        "end": 59,
        "string": "hurt"
      },
      {
        "start": 59,
        "end": 60,
        "string": " "
      },
      {
        "start": 60,
        "end": 67,
        "string": "Friday"
      },
      {
        "start": 67,
        "end": 68,
        "string": " "
      },
      {
        "start": 68,
        "end": 71,
        "string": "in"
      },
      {
        "start": 71,
        "end": 72,
        "string": " "
      },
      {
        "start": 72,
        "end": 80,
        "string": "violent"
      },
      {
        "start": 80,
        "end": 81,
        "string": " "
      },
      {
        "start": 81,
        "end": 89,
        "string": "clashes"
      },
      {
        "start": 89,
        "end": 90,
        "string": " "
      },
      {
        "start": 90,
        "end": 98,
        "string": "between"
      },
      {
        "start": 98,
        "end": 99,
        "string": " "
      },
      {
        "start": 99,
        "end": 106,
        "string": "police"
      },
      {
        "start": 106,
        "end": 107,
        "string": " "
      },
      {
        "start": 107,
        "end": 111,
        "string": "and"
      },
      {
        "start": 111,
        "end": 112,
        "string": " "
      },
      {
        "start": 112,
        "end": 123,
        "string": "protesters"
      },
      {
        "start": 123,
        "end": 124,
        "string": " "
      },
      {
        "start": 124,
        "end": 127,
        "string": "in"
      },
      {
        "start": 127,
        "end": 128,
        "string": " "
      },
      {
        "start": 128,
        "end": 132,
        "string": "the"
      },
      {
        "start": 132,
        "end": 133,
        "string": " "
      },
      {
        "start": 133,
        "end": 142,
        "string": "Algerian"
      },
      {
        "start": 142,
        "end": 143,
        "string": " "
      },
      {
        "start": 143,
        "end": 151,
        "string": "capital"
      },
      {
        "start": 151,
        "end": 152,
        "string": " "
      },
      {
        "start": 152,
        "end": 154,
        "string": ","
      },
      {
        "start": 154,
        "end": 155,
        "string": " "
      },
      {
        "start": 155,
        "end": 159,
        "string": "AFP"
      },
      {
        "start": 159,
        "end": 160,
        "string": " "
      },
      {
        "start": 160,
        "end": 172,
        "string": "journalists"
      },
      {
        "start": 172,
        "end": 173,
        "string": " "
      },
      {
        "start": 173,
        "end": 178,
        "string": "said"
      },
      {
        "start": 178,
        "end": 179,
        "string": " "
      },
      {
        "start": 179,
        "end": 181,
        "string": ","
      },
      {
        "start": 181,
        "end": 182,
        "string": " "
      },
      {
        "start": 182,
        "end": 189,
        "string": "during"
      },
      {
        "start": 189,
        "end": 190,
        "string": " "
      },
      {
        "start": 190,
        "end": 205,
        "string": "demonstrations"
      },
      {
        "start": 205,
        "end": 206,
        "string": " "
      },
      {
        "start": 206,
        "end": 214,
        "string": "against"
      },
      {
        "start": 214,
        "end": 215,
        "string": " "
      },
      {
        "start": 215,
        "end": 217,
        "string": "a"
      },
      {
        "start": 217,
        "end": 218,
        "string": " "
      },
      {
        "start": 218,
        "end": 222,
        "string": "bid"
      },
      {
        "start": 222,
        "end": 223,
        "string": " "
      },
      {
        "start": 223,
        "end": 226,
        "string": "by"
      },
      {
        "start": 226,
        "end": 227,
        "string": " "
      },
      {
        "start": 227,
        "end": 234,
        "string": "ailing"
      },
      {
        "start": 234,
        "end": 235,
        "string": " "
      },
      {
        "start": 235,
        "end": 245,
        "string": "President"
      },
      {
        "start": 245,
        "end": 246,
        "string": " "
      },
      {
        "start": 246,
        "end": 256,
        "string": "Abdelaziz"
      },
      {
        "start": 256,
        "end": 257,
        "string": " "
      },
      {
        "start": 257,
        "end": 268,
        "string": "Bouteflika"
      },
      {
        "start": 268,
        "end": 269,
        "string": " "
      },
      {
        "start": 269,
        "end": 272,
        "string": "to"
      },
      {
        "start": 272,
        "end": 273,
        "string": " "
      },
      {
        "start": 273,
        "end": 278,
        "string": "seek"
      },
      {
        "start": 278,
        "end": 279,
        "string": " "
      },
      {
        "start": 279,
        "end": 281,
        "string": "a"
      },
      {
        "start": 281,
        "end": 282,
        "string": " "
      },
      {
        "start": 282,
        "end": 288,
        "string": "fifth"
      },
      {
        "start": 288,
        "end": 289,
        "string": " "
      },
      {
        "start": 289,
        "end": 294,
        "string": "term"
      },
      {
        "start": 294,
        "end": 295,
        "string": " "
      },
      {
        "start": 295,
        "end": 297,
        "string": "."
      },
      {
        "start": 297,
        "end": 298,
        "string": " "
      },
      {
        "start": 298,
        "end": 300,
        "string": "A"
      },
      {
        "start": 300,
        "end": 301,
        "string": " "
      },
      {
        "start": 301,
        "end": 308,
        "string": "number"
      },
      {
        "start": 308,
        "end": 309,
        "string": " "
      },
      {
        "start": 309,
        "end": 312,
        "string": "of"
      },
      {
        "start": 312,
        "end": 313,
        "string": " "
      },
      {
        "start": 313,
        "end": 317,
        "string": "the"
      },
      {
        "start": 317,
        "end": 318,
        "string": " "
      },
      {
        "start": 318,
        "end": 326,
        "string": "injured"
      },
      {
        "start": 326,
        "end": 327,
        "string": " "
      },
      {
        "start": 327,
        "end": 336,
        "string": "suffered"
      },
      {
        "start": 336,
        "end": 337,
        "string": " "
      },
      {
        "start": 337,
        "end": 342,
        "string": "head"
      },
      {
        "start": 342,
        "end": 343,
        "string": " "
      },
      {
        "start": 343,
        "end": 350,
        "string": "wounds"
      },
      {
        "start": 350,
        "end": 351,
        "string": " "
      },
      {
        "start": 351,
        "end": 357,
        "string": "after"
      },
      {
        "start": 357,
        "end": 358,
        "string": " "
      },
      {
        "start": 358,
        "end": 364,
        "string": "being"
      },
      {
        "start": 364,
        "end": 365,
        "string": " "
      },
      {
        "start": 365,
        "end": 369,
        "string": "hit"
      },
      {
        "start": 369,
        "end": 370,
        "string": " "
      },
      {
        "start": 370,
        "end": 373,
        "string": "by"
      },
      {
        "start": 373,
        "end": 374,
        "string": " "
      },
      {
        "start": 374,
        "end": 381,
        "string": "batons"
      },
      {
        "start": 381,
        "end": 382,
        "string": " "
      },
      {
        "start": 382,
        "end": 385,
        "string": "or"
      },
      {
        "start": 385,
        "end": 386,
        "string": " "
      },
      {
        "start": 386,
        "end": 393,
        "string": "stones"
      },
      {
        "start": 393,
        "end": 394,
        "string": " "
      },
      {
        "start": 394,
        "end": 401,
        "string": "thrown"
      },
      {
        "start": 401,
        "end": 402,
        "string": " "
      },
      {
        "start": 402,
        "end": 405,
        "string": "by"
      },
      {
        "start": 405,
        "end": 406,
        "string": " "
      },
      {
        "start": 406,
        "end": 413,
        "string": "police"
      },
      {
        "start": 413,
        "end": 414,
        "string": " "
      },
      {
        "start": 414,
        "end": 419,
        "string": "back"
      },
      {
        "start": 419,
        "end": 420,
        "string": " "
      },
      {
        "start": 420,
        "end": 423,
        "string": "at"
      },
      {
        "start": 423,
        "end": 424,
        "string": " "
      },
      {
        "start": 424,
        "end": 438,
        "string": "demonstrators"
      },
      {
        "start": 438,
        "end": 439,
        "string": " "
      },
      {
        "start": 439,
        "end": 443,
        "string": "who"
      },
      {
        "start": 443,
        "end": 444,
        "string": " "
      },
      {
        "start": 444,
        "end": 448,
        "string": "had"
      },
      {
        "start": 448,
        "end": 449,
        "string": " "
      },
      {
        "start": 449,
        "end": 459,
        "string": "initially"
      },
      {
        "start": 459,
        "end": 460,
        "string": " "
      },
      {
        "start": 460,
        "end": 467,
        "string": "hurled"
      },
      {
        "start": 467,
        "end": 468,
        "string": " "
      },
      {
        "start": 468,
        "end": 473,
        "string": "them"
      },
      {
        "start": 473,
        "end": 474,
        "string": " "
      },
      {
        "start": 474,
        "end": 477,
        "string": "at"
      },
      {
        "start": 477,
        "end": 478,
        "string": " "
      },
      {
        "start": 478,
        "end": 487,
        "string": "officers"
      },
      {
        "start": 487,
        "end": 488,
        "string": " "
      },
      {
        "start": 488,
        "end": 490,
        "string": "."
      },
      {
        "start": 490,
        "end": 491,
        "string": " "
      },
      {
        "start": 491,
        "end": 496,
        "string": "Riot"
      },
      {
        "start": 496,
        "end": 497,
        "string": " "
      },
      {
        "start": 497,
        "end": 504,
        "string": "police"
      },
      {
        "start": 504,
        "end": 505,
        "string": " "
      },
      {
        "start": 505,
        "end": 510,
        "string": "also"
      },
      {
        "start": 510,
        "end": 511,
        "string": " "
      },
      {
        "start": 511,
        "end": 517,
        "string": "fired"
      },
      {
        "start": 517,
        "end": 518,
        "string": " "
      },
      {
        "start": 518,
        "end": 523,
        "string": "tear"
      },
      {
        "start": 523,
        "end": 524,
        "string": " "
      },
      {
        "start": 524,
        "end": 528,
        "string": "gas"
      },
      {
        "start": 528,
        "end": 529,
        "string": " "
      },
      {
        "start": 529,
        "end": 532,
        "string": "to"
      },
      {
        "start": 532,
        "end": 533,
        "string": " "
      },
      {
        "start": 533,
        "end": 537,
        "string": "try"
      },
      {
        "start": 537,
        "end": 538,
        "string": " "
      },
      {
        "start": 538,
        "end": 541,
        "string": "to"
      },
      {
        "start": 541,
        "end": 542,
        "string": " "
      },
      {
        "start": 542,
        "end": 551,
        "string": "disperse"
      },
      {
        "start": 551,
        "end": 552,
        "string": " "
      },
      {
        "start": 552,
        "end": 554,
        "string": "a"
      },
      {
        "start": 554,
        "end": 555,
        "string": " "
      },
      {
        "start": 555,
        "end": 561,
        "string": "group"
      },
      {
        "start": 561,
        "end": 562,
        "string": " "
      },
      {
        "start": 562,
        "end": 565,
        "string": "of"
      },
      {
        "start": 565,
        "end": 566,
        "string": " "
      },
      {
        "start": 566,
        "end": 573,
        "string": "around"
      },
      {
        "start": 573,
        "end": 574,
        "string": " "
      },
      {
        "start": 574,
        "end": 578,
        "string": "200"
      },
      {
        "start": 578,
        "end": 579,
        "string": " "
      },
      {
        "start": 579,
        "end": 585,
        "string": "young"
      },
      {
        "start": 585,
        "end": 586,
        "string": " "
      },
      {
        "start": 586,
        "end": 593,
        "string": "people"
      },
      {
        "start": 593,
        "end": 594,
        "string": " "
      },
      {
        "start": 594,
        "end": 596,
        "string": ","
      },
      {
        "start": 596,
        "end": 597,
        "string": " "
      },
      {
        "start": 597,
        "end": 604,
        "string": "around"
      },
      {
        "start": 604,
        "end": 605,
        "string": " "
      },
      {
        "start": 605,
        "end": 609,
        "string": "1.5"
      },
      {
        "start": 609,
        "end": 610,
        "string": " "
      },
      {
        "start": 610,
        "end": 621,
        "string": "kilometres"
      },
      {
        "start": 621,
        "end": 622,
        "string": " "
      },
      {
        "start": 622,
        "end": 627,
        "string": "from"
      },
      {
        "start": 627,
        "end": 628,
        "string": " "
      },
      {
        "start": 628,
        "end": 632,
        "string": "the"
      },
      {
        "start": 632,
        "end": 633,
        "string": " "
      },
      {
        "start": 633,
        "end": 646,
        "string": "presidential"
      },
      {
        "start": 646,
        "end": 647,
        "string": " "
      },
      {
        "start": 647,
        "end": 654,
        "string": "palace"
      },
      {
        "start": 654,
        "end": 655,
        "string": " "
      },
      {
        "start": 655,
        "end": 657,
        "string": "."
      },
      {
        "start": 657,
        "end": 658,
        "string": " "
      }
    ]
  }
}